README.rst
setup.py
sanic_sentry/__init__.py
sanic_sentry_error_handler.egg-info/PKG-INFO
sanic_sentry_error_handler.egg-info/SOURCES.txt
sanic_sentry_error_handler.egg-info/dependency_links.txt
sanic_sentry_error_handler.egg-info/requires.txt
sanic_sentry_error_handler.egg-info/top_level.txt