Metadata-Version: 1.1
Name: sanic-sentry-error-handler
Version: 0.1.2
Summary: Sanic error handlert that integrates with Sentry
Home-page: https://github.com/ekampf/sanic-sentry-error-handler
Author: Eran Kampf
Author-email: UNKNOWN
License: MIT
Keywords: sanic,sentry
Platform: Any
Classifier: Development Status :: 3 - Alpha
Classifier: Intended Audience :: Developers
Classifier: License :: OSI Approved :: MIT License
Classifier: Natural Language :: English
Classifier: Operating System :: OS Independent
Classifier: Programming Language :: Python
Classifier: Programming Language :: Python :: 3.5
Classifier: Programming Language :: Python :: 3.6
Classifier: Programming Language :: Python :: 3 :: Only
Classifier: Topic :: Software Development :: Libraries :: Python Modules
Classifier: Topic :: Software Development :: Testing
Classifier: Topic :: Utilities
